table_schema_resource_template/cli.py
table_schema_resource_template-0.1.3.dist-info/LICENSE
table_schema_resource_template-0.1.3.dist-info/METADATA
table_schema_resource_template-0.1.3.dist-info/WHEEL
table_schema_resource_template-0.1.3.dist-info/entry_points.txt
table_schema_resource_template-0.1.3.dist-info/top_level.txt
table_schema_resource_template-0.1.3.dist-info/RECORD
