Metadata-Version: 2.1
Name: table-schema-resource-template
Version: 0.1.3
Summary: Generate a resource file template from a Table Schema JSON file
Home-page: https://framagit.org/opendataschema/table-schema-resource-template
Author: Christophe Benz
Author-email: christophe.benz@jailbreak.paris
License: MIT
Platform: UNKNOWN
Classifier: Development Status :: 4 - Beta
Classifier: Intended Audience :: Developers
Classifier: Topic :: Software Development :: Libraries :: Python Modules
Classifier: Operating System :: OS Independent
Classifier: License :: OSI Approved :: MIT License
Classifier: Programming Language :: Python :: 3
Requires-Dist: iso8601
Requires-Dist: tableschema (>=1.5.1)
Requires-Dist: xlsxwriter (>=1.1.8)
